setup.py
disboard/code.py
disboard.egg-info/PKG-INFO
disboard.egg-info/SOURCES.txt
disboard.egg-info/dependency_links.txt
disboard.egg-info/top_level.txt