Metadata-Version: 2.1
Name: disboard
Version: 1.0
Summary: disboard manager.
Author: helper
License: MIT
Keywords: style
Classifier: Development Status :: 5 - Production/Stable
